changelogd/__init__.py
changelogd/__main__.py
changelogd/changelogd.py
changelogd/cli.py
changelogd/commands.py
changelogd/computed_values.py
changelogd/config.py
changelogd/resolver.py
changelogd/utils.py
changelogd/templates/README.md
changelogd/templates/md/entry.md
changelogd/templates/md/main.md
changelogd/templates/md/release.md
changelogd/templates/rst/entry.rst
changelogd/templates/rst/main.rst
changelogd/templates/rst/release.rst
changelogd-0.1.9.dist-info/LICENSE
changelogd-0.1.9.dist-info/METADATA
changelogd-0.1.9.dist-info/WHEEL
changelogd-0.1.9.dist-info/entry_points.txt
changelogd-0.1.9.dist-info/top_level.txt
changelogd-0.1.9.dist-info/RECORD
