Metadata-Version: 2.1
Name: changelogd
Version: 0.1.9
Summary: Changelogs without conflicts.
Home-page: https://github.com/aklajnert/changelogd
Author: Andrzej Klajnert
Author-email: python@aklajnert.pl
License: MIT license
Keywords: changelogd
Classifier: Development Status :: 4 - Beta
Classifier: Intended Audience :: Developers
Classifier: License :: OSI Approved :: MIT License
Classifier: Natural Language :: English
Classifier: Programming Language :: Python :: 3
Classifier: Programming Language :: Python :: 3.6
Classifier: Programming Language :: Python :: 3.7
Classifier: Programming Language :: Python :: 3.8
Classifier: Programming Language :: Python :: 3.9
Classifier: Programming Language :: Python :: 3.10
Classifier: Programming Language :: Python :: 3.11
Classifier: Programming Language :: Python :: 3.12
Requires-Python: >=3.6
License-File: LICENSE
Requires-Dist: Click>=8.1.7
Requires-Dist: Jinja2>=3.1.3
Requires-Dist: toml>=0.10.2
Requires-Dist: ruamel.yaml>=0.18.6
Provides-Extra: test
Requires-Dist: pytest>=5; extra == "test"
Requires-Dist: pyfakefs==5.4; extra == "test"
Requires-Dist: pytest-subprocess; extra == "test"
Provides-Extra: dev
Requires-Dist: bump2version==1.0.1; extra == "dev"
Requires-Dist: wheel==0.43.0; extra == "dev"
Requires-Dist: flake8==7.0.0; extra == "dev"
Requires-Dist: nox==2024.3.2; extra == "dev"
Requires-Dist: mypy==1.9.0; extra == "dev"
Provides-Extra: docs
Requires-Dist: sphinx; extra == "docs"
